myfm/__init__.py
myfm/_myfm.cpython-310-aarch64-linux-gnu.so
myfm/_myfm.pyi
myfm/_version.py
myfm/base.py
myfm/gibbs.py
myfm/variational.py
myfm/utils/__init__.py
myfm/utils/dummy_data.py
myfm/utils/benchmark_data/__init__.py
myfm/utils/benchmark_data/loader_base.py
myfm/utils/benchmark_data/movielens100k_data.py
myfm/utils/benchmark_data/movielens10M_data.py
myfm/utils/benchmark_data/movielens1M_data.py
myfm/utils/callbacks/__init__.py
myfm/utils/callbacks/libfm.py
myfm/utils/encoders/__init__.py
myfm/utils/encoders/base.py
myfm/utils/encoders/binning.py
myfm/utils/encoders/categorical.py
myfm/utils/encoders/multi_value.py
myfm-0.4.0.dist-info/METADATA
myfm-0.4.0.dist-info/WHEEL
myfm-0.4.0.dist-info/RECORD
myfm-0.4.0.dist-info/licenses/LICENSE
