Metadata-Version: 2.4
Name: myfm
Version: 0.4.0
Summary: Yet another Bayesian factorization machines.
Author-Email: Tomoki Ohtsuki <tomoki.ohtsuki.19937@outlook.jp>
License-Expression: MIT
Project-URL: Homepage, https://github.com/tohtsky/myFM
Requires-Dist: numpy>=2.0
Requires-Dist: scipy>=1.0
Requires-Dist: tqdm>=4
Requires-Dist: pandas>=2.2.0
Requires-Dist: typing-extensions>=4.0.0
